bayescorner/__init__.py
bayescorner/__version__.py
bayescorner/compute_sigma_level.py
bayescorner/corner.py
bayescorner-0.1.0.dist-info/LICENSE
bayescorner-0.1.0.dist-info/METADATA
bayescorner-0.1.0.dist-info/WHEEL
bayescorner-0.1.0.dist-info/top_level.txt
bayescorner-0.1.0.dist-info/RECORD
