Metadata-Version: 2.1
Name: bayescorner
Version: 0.1.0
Summary: A simple corner got my fits
Home-page: https://github.com/grburgess/bayescorner
Author: J. Michael Burgess
Author-email: jmichaelburgess@gmail.com
License: BSD
Platform: UNKNOWN
Requires-Python: >=2.7.0
Requires-Dist: numpy
Requires-Dist: matplotlib
Requires-Dist: betagen
Requires-Dist: scipy
